jobappfiller/__init__.py
jobappfiller/cli.py
jobappfiller/tools/__init__.py
jobappfiller/tools/app.py
jobappfiller/tools/cli.py
jobappfiller/tools/parse_job_config.py
jobappfiller/tools/resume_data_gen.py
jobappfiller/util/__init__.py
jobappfiller/util/logger.py
jobappfiller-1.1.2.dist-info/licenses/LICENSE
jobappfiller-1.1.2.dist-info/METADATA
jobappfiller-1.1.2.dist-info/WHEEL
jobappfiller-1.1.2.dist-info/entry_points.txt
jobappfiller-1.1.2.dist-info/top_level.txt
jobappfiller-1.1.2.dist-info/RECORD
