Metadata-Version: 2.4
Name: jobappfiller
Version: 1.1.2
Summary: Automatically fill in experience for online job applications.
Author-email: Ash Hellwig <ahellwig.dev@gmail.com>
License-Expression: AGPL-3.0
Project-URL: Homepage, https://github.com/ashellwig/jobappfiller
Project-URL: Repository, https://github.com/ashellwig/jobappfiller.git
Project-URL: Issues, https://github.com/ashellwig/jobappfiller/issues
Keywords: selenium,browser,cli,jobs,application,autofill,auto-fill
Classifier: Development Status :: 4 - Beta
Classifier: Environment :: Console
Classifier: Intended Audience :: Developers
Classifier: Intended Audience :: End Users/Desktop
Classifier: Operating System :: POSIX
Classifier: Programming Language :: Python :: 3.13
Requires-Python: >=3.13
License-File: LICENSE
Requires-Dist: build==1.2.2.post1
Requires-Dist: click==8.2.0
Requires-Dist: keyring==25.6.0
Requires-Dist: pydocstyle==6.3.0
Requires-Dist: pyinstaller==6.13.0
Requires-Dist: pylint==3.3.7
Requires-Dist: pyperclip==1.9.0
Requires-Dist: pytest==8.3.5
Requires-Dist: rich==14.0.0
Requires-Dist: tomlkit==0.13.2
Requires-Dist: twine==6.1.0
Requires-Dist: yapf==0.43.0
Dynamic: license-file
